shared_auth/__init__.py
shared_auth/backends_django.py
shared_auth/config.py
shared_auth/dependencies_fastapi.py
shared_auth/jwt_handler.py
shared_auth/utils.py
tests/__init__.py
tests/test_fastapi.py
tests/test_jwt.py
onflow_wms_shared_auth-0.1.6.dist-info/METADATA
onflow_wms_shared_auth-0.1.6.dist-info/WHEEL
onflow_wms_shared_auth-0.1.6.dist-info/top_level.txt
onflow_wms_shared_auth-0.1.6.dist-info/RECORD
