Metadata-Version: 2.4
Name: onflow-wms-shared-auth
Version: 0.1.6
Summary: Shared authentication module for Onflow WMS
Author-email: N-H Logistics <dev@nhlogistics.vn>
Requires-Python: >=3.9
